pytextrust-0.12.0.dist-info/METADATA
pytextrust-0.12.0.dist-info/WHEEL
pytextrust-0.12.0.dist-info/licenses/LICENSE
pytextrust/__init__.py
pytextrust/constants.py
pytextrust/entities.py
pytextrust/ents_plot.py
pytextrust/misc.py
pytextrust/normalization.py
pytextrust/pytextrust.cpython-310-x86_64-linux-gnu.so
pytextrust/regex_operator.py
pytextrust/replacer.py
pytextrust/similarity.py
pytextrust/tests/__init__.py
pytextrust/tests/data/non_unicode_test.json
pytextrust/tests/test_misc.py
pytextrust/tests/test_normalization.py
pytextrust/tests/test_regex_operator.py
pytextrust/tests/test_replacer.py
pytextrust/tests/test_similarity.py
pytextrust/tests/test_text_dist.py
pytextrust/tests/test_token.py
pytextrust/text_dist.py
pytextrust/token.py
pytextrust-0.12.0.dist-info/RECORD
