Metadata-Version: 2.4
Name: pytextrust
Version: 0.12.0
Classifier: License :: OSI Approved :: MIT License
Classifier: Programming Language :: Python :: 3
Classifier: Programming Language :: Python :: Implementation :: CPython
Classifier: Programming Language :: Python :: Implementation :: PyPy
Classifier: Programming Language :: Rust
Requires-Dist: pydantic
Requires-Dist: typing
Requires-Dist: regex
License-File: LICENSE
Summary: Library designed as a python wrapper to unleash Rust text processing power combined with Python
Keywords: text-processing,regex-matching,entity-system,literal-replacement
Home-Page: https://gitlab.com/g6313/pytextrust
Author: Guillermo Gonzalez <guillermogsjc@gmail.com>
Author-email: Guillermo Gonzalez <guillermogsjc@gmail.com>
License: MIT
Requires-Python: >=3.7
Project-URL: Homepage, https://gitlab.com/g6313/pytextrust
